tests/__init__.py
tests/test_uzireader.py
tests/test_uzivalidate.py
uzireader/__init__.py
uzireader/consts.py
uzireader/exceptions.py
uzireader/uzipassuser.py
uzireader/uzipassvalidator.py
pUzi-1.2.dist-info/LICENSE.pdf
pUzi-1.2.dist-info/LICENSE.txt
pUzi-1.2.dist-info/LICENSES.md
pUzi-1.2.dist-info/METADATA
pUzi-1.2.dist-info/WHEEL
pUzi-1.2.dist-info/top_level.txt
pUzi-1.2.dist-info/RECORD
