Metadata-Version: 2.1
Name: pUzi
Version: 1.2
Summary: pUzi, python3, Proficient UZI pass reader in python.
Home-page: https://github.com/minvws/pUzi-python
Author: Jan Klopper
Author-email: jan@underdark.nl
License: European Union Public Licence 1.2 (EUPL 1.2)
Keywords: Uzipas,pUzi
Platform: UNKNOWN
Classifier: Development Status :: 4 - Beta
Classifier: Intended Audience :: Developers
Classifier: License :: OSI Approved :: European Union Public Licence 1.2 (EUPL 1.2)
Classifier: Operating System :: POSIX :: Linux
Classifier: Programming Language :: Python
Classifier: Programming Language :: Python :: 3.6
Requires-Python: >=3.6
Requires-Dist: cryptography (>=3.1)
